time_calcfreename/__init__.py
time_calcfreename/time_calculator.py
time_calcfreename-0.0.4.dist-info/LICENSE
time_calcfreename-0.0.4.dist-info/METADATA
time_calcfreename-0.0.4.dist-info/WHEEL
time_calcfreename-0.0.4.dist-info/top_level.txt
time_calcfreename-0.0.4.dist-info/RECORD
