Metadata-Version: 2.1
Name: time_calcfreename
Version: 0.0.4
Summary: Hi Mai
Author: Someone
Author-email: <mail@neuralnine.com>
Classifier: Development Status :: 1 - Planning
Classifier: Intended Audience :: Developers
Classifier: Programming Language :: Python :: 3
Classifier: Operating System :: Unix
Classifier: Operating System :: MacOS :: MacOS X
Classifier: Operating System :: Microsoft :: Windows
License-File: LICENSE
